[{"countryName":"USA","gdp":"16237.75"},{"countryName":"China","gdp":"9020.31"},{"countryName":"Japan","gdp":"5149.90"},{"countryName":"Germany","gdp":"3597.97"},{"countryName":"France","gdp":"2739.27"},{"countryName":"Brazil","gdp":"2456.66"},{"countryName":"United Kingdom","gdp":"2422.92"},{"countryName":"Russia","gdp":"2213.57"},{"countryName":"Italy","gdp":"2076.01"},{"countryName":"India","gdp":"1972.84"},{"countryName":"Canada","gdp":"1843.75"},{"countryName":"Australia","gdp":"1589.12"},{"countryName":"Mexico","gdp":"1274.97"},{"countryName":"Republic of Korea","gdp":"1258.59"},{"countryName":"Indonesia","gdp":"946.39"},{"countryName":"Turkey","gdp":"851.82"},{"countryName":"Saudi Arabia","gdp":"745.62"},{"countryName":"Argentina","gdp":"498.70"},{"countryName":"South Africa","gdp":"375.99"}]